{
  "publicPath": "/_nuxt/",
  "all": [
    "../server/index.spa.html",
    "0b50955639e75a353c93.js",
    "2299f42880cff3854be3.js",
    "37b636610145a224f0c8.js",
    "LICENSES",
    "a57f172db5f316553d50.js",
    "fe2cce4b5fde70e1b27f.js",
    "fonts/3e1af3e.ttf",
    "fonts/c18b935.ttf",
    "img/90c171b.jpg"
  ],
  "initial": [
    "2299f42880cff3854be3.js",
    "a57f172db5f316553d50.js",
    "fe2cce4b5fde70e1b27f.js"
  ],
  "async": [
    "0b50955639e75a353c93.js",
    "37b636610145a224f0c8.js"
  ],
  "modules": {
    "11299520": [
      5
    ],
    "23698058": [
      5
    ],
    "66403237": [
      5
    ],
    "74708429": [
      5
    ],
    "75564376": [
      5
    ],
    "77387821": [
      5
    ],
    "78175384": [
      5
    ],
    "79712152": [
      3
    ],
    "1643b270": [
      5
    ],
    "f2475c5e": [
      5
    ],
    "edddcf0a": [
      5
    ],
    "ffb0cb5e": [
      5
    ],
    "a4b6f476": [
      5
    ],
    "e9c27a6c": [
      5
    ],
    "06ef5b0f": [
      5
    ],
    "6078452a": [
      5
    ],
    "1d05e7ec": [
      5
    ],
    "b3a779e4": [
      5
    ],
    "3c7932db": [
      5
    ],
    "ea99b2d6": [
      5
    ],
    "209480d0": [
      5
    ],
    "98fd131e": [
      6,
      8,
      7
    ],
    "860160b4": [
      6,
      8,
      7
    ],
    "398eb0bf": [
      5
    ],
    "370b7c3c": [
      5
    ],
    "6cb6b576": [
      5
    ],
    "f88c098e": [
      5
    ],
    "0c02f3d0": [
      5
    ],
    "e0c8a9b2": [
      5
    ],
    "64edda96": [
      5
    ],
    "653c7ec9": [
      5
    ],
    "4704db64": [
      5
    ],
    "4bf2bfb0": [
      5
    ],
    "20f6ae62": [
      5
    ],
    "4f738536": [
      5
    ],
    "e2c5afdc": [
      5
    ],
    "abc3e196": [
      5
    ],
    "f960c000": [
      5
    ],
    "22ef87ab": [
      5
    ],
    "b188d9c2": [
      5
    ],
    "7916f2e7": [
      5
    ],
    "13aca079": [
      5
    ],
    "9e1b258c": [
      5
    ],
    "0ef877aa": [
      5
    ],
    "4ffdc82d": [
      5
    ],
    "44801bf3": [
      5
    ],
    "49a1ccc0": [
      5
    ],
    "ef65ef38": [
      5
    ],
    "23cc65a5": [
      5
    ],
    "9443145e": [
      6,
      8,
      7
    ],
    "291634dd": [
      6,
      8,
      7
    ],
    "0abeeb9b": [
      6,
      8,
      7
    ],
    "5e6e58f9": [
      6,
      8,
      7
    ],
    "639c2e29": [
      6,
      8,
      7
    ],
    "794494f0": [
      6,
      8,
      7
    ],
    "00bbf021": [
      6,
      8,
      7
    ],
    "339624ee": [
      5
    ],
    "1974021c": [
      5
    ],
    "7ae257c9": [
      5
    ],
    "b4af9030": [
      5
    ],
    "017269b2": [
      5
    ],
    "45efb912": [
      5
    ],
    "197647f7": [
      5
    ],
    "436d639d": [
      5
    ],
    "88407bbe": [
      5
    ],
    "5d359b4a": [
      5
    ],
    "dcc2cce8": [
      5
    ],
    "6e1f5996": [
      5
    ],
    "4ff8e24a": [
      5
    ],
    "05defdf8": [
      5
    ],
    "50f36ec7": [
      5
    ],
    "75446e5c": [
      5
    ],
    "74c74ec6": [
      5
    ],
    "0f8997c2": [
      5
    ],
    "1ad15b86": [
      5
    ],
    "196f7666": [
      5
    ],
    "733bb47e": [
      5
    ],
    "aa53f580": [
      5
    ],
    "5f01f827": [
      5
    ],
    "499ec956": [
      5
    ],
    "2644b9df": [
      5
    ],
    "4a52cd33": [
      5
    ],
    "089ce3b5": [
      5
    ],
    "064b1506": [
      5
    ],
    "4fce2588": [
      5
    ],
    "4ef72b2b": [
      5
    ],
    "86d42808": [
      5
    ],
    "41f179c0": [
      5
    ],
    "0f5a2948": [
      5
    ],
    "b5f4cdce": [
      5
    ],
    "7021b747": [
      5
    ],
    "ab531954": [
      5
    ],
    "1493fe42": [
      5
    ],
    "9063b914": [
      5
    ],
    "6b684948": [
      5
    ],
    "435c6795": [
      5
    ],
    "96b328f2": [
      5
    ],
    "02cb5d17": [
      5
    ],
    "740d0d72": [
      5
    ],
    "00f6f347": [
      5
    ],
    "7a70c631": [
      5
    ],
    "6ab9b1b8": [
      6,
      8,
      7
    ],
    "7b84e684": [
      5
    ],
    "0a8af2b3": [
      5
    ],
    "65c14b76": [
      6,
      8,
      7
    ],
    "5cb02460": [
      5
    ],
    "1ac86a5f": [
      5
    ],
    "3590a705": [
      5
    ],
    "3486957c": [
      5
    ],
    "3aad5f66": [
      5
    ],
    "3996e899": [
      5
    ],
    "40eab760": [
      5
    ],
    "203b0848": [
      5
    ],
    "3c5660eb": [
      5
    ],
    "36d919cd": [
      5
    ],
    "4e549aaa": [
      5
    ],
    "47c848e2": [
      5
    ],
    "4bb492b3": [
      5
    ],
    "6cac9ae8": [
      5
    ],
    "3391f20a": [
      5
    ],
    "717497c3": [
      5
    ],
    "6dace6bd": [
      5
    ],
    "51f55bbe": [
      5
    ],
    "266e57d2": [
      5
    ],
    "0a60ab86": [
      5
    ],
    "ec72c6b2": [
      5
    ],
    "455882cf": [
      5
    ],
    "5f6253ca": [
      5
    ],
    "ed562508": [
      5
    ],
    "eff4a150": [
      5
    ],
    "41b9b292": [
      5
    ],
    "4dee2bf4": [
      5
    ],
    "0de3c7cb": [
      5
    ],
    "35cbf4d9": [
      5
    ],
    "3f45e5cd": [
      5
    ],
    "ea38062e": [
      5
    ],
    "d613cf70": [
      5
    ],
    "2c3373d6": [
      5
    ],
    "86567c9a": [
      5
    ],
    "d82b48d4": [
      5
    ],
    "06d1ec18": [
      5
    ],
    "4dc246dc": [
      5
    ],
    "6caa184e": [
      5
    ],
    "2ff08499": [
      6,
      8,
      7
    ],
    "0796c477": [
      6,
      8,
      7
    ],
    "66dfb1a5": [
      6,
      8,
      7
    ],
    "24151bfa": [
      6,
      8,
      7
    ],
    "6c7d4496": [
      6,
      8,
      7
    ],
    "fb08a688": [
      6,
      8,
      7
    ],
    "33ee68b8": [
      6,
      8,
      7
    ],
    "3ec20778": [
      6,
      8,
      7
    ],
    "71dc0314": [
      6,
      8,
      7
    ],
    "589b69d3": [
      6,
      8,
      7
    ],
    "759a60b5": [
      6,
      8,
      7
    ],
    "d21a999e": [
      6,
      8,
      7
    ],
    "c59729da": [
      6,
      8,
      7
    ],
    "9d0ea73e": [
      6,
      8,
      7
    ],
    "6310b97a": [
      6,
      8,
      7
    ],
    "0c1385c0": [
      6,
      8,
      7
    ],
    "359f67bc": [
      6,
      8,
      7
    ],
    "708612e9": [
      6,
      8,
      7
    ],
    "136575c7": [
      6,
      8,
      7
    ],
    "8bab68c6": [
      5
    ],
    "54acbbdc": [
      5
    ],
    "70036e7d": [
      5
    ],
    "fa9f1c0a": [
      5
    ],
    "45b95c04": [
      6,
      8,
      7
    ],
    "f85cdc1c": [
      6,
      8,
      7
    ],
    "46e216ab": [
      6,
      8,
      7
    ],
    "85c9e5ac": [
      5
    ],
    "6c8e0f52": [
      5
    ],
    "28c48888": [
      5
    ],
    "73cc57a5": [
      5
    ],
    "7d962305": [
      5
    ],
    "2b0cd194": [
      5
    ],
    "a5ce5aba": [
      5
    ],
    "ab3cb49e": [
      5
    ],
    "35feda59": [
      5
    ],
    "710f1680": [
      5
    ],
    "1ef41afb": [
      5
    ],
    "462debc8": [
      5
    ],
    "1f594709": [
      5
    ],
    "5a3faeb0": [
      5
    ],
    "5ed779fc": [
      5
    ],
    "220028c7": [
      5
    ],
    "2abf7d84": [
      5
    ],
    "a6f3f95e": [
      5
    ],
    "56e8c0d6": [
      6,
      8,
      7
    ],
    "3510e266": [
      1,
      9
    ],
    "0f00f06e": [
      1,
      9
    ],
    "5c9fbbe7": [
      3
    ],
    "36c597bc": [
      3
    ],
    "dc0c9d4e": [
      3
    ],
    "432b6006": [
      1,
      9
    ],
    "1dfbe905": [
      1,
      9
    ],
    "243da0e7": [
      1,
      9
    ],
    "2ac89194": [
      1,
      9
    ],
    "26eb3914": [
      1,
      9
    ],
    "82842cd4": [
      3
    ],
    "b9477f9c": [
      3
    ],
    "70d09310": [
      3
    ],
    "d5b7d3c2": [
      3
    ],
    "c93463fe": [
      3
    ],
    "86b7be2c": [
      3
    ],
    "7e996548": [
      3
    ],
    "8a5f44de": [
      3
    ],
    "3783a4f3": [
      3
    ],
    "c23b93c2": [
      3
    ],
    "499c9006": [
      3
    ],
    "1d730582": [
      3
    ],
    "0489aa86": [
      1,
      9
    ]
  },
  "assetsMapping": {
    "0b50955639e75a353c93.js": "2aff1868",
    "2299f42880cff3854be3.js": "6fca0322",
    "37b636610145a224f0c8.js": "2a130dde",
    "a57f172db5f316553d50.js": "0859c165",
    "fe2cce4b5fde70e1b27f.js": "1a3ae26b"
  }
}